COPYING
Changelog
MANIFEST.in
README
README.rst
THANKS
requirements.txt
setup.cfg
setup.py
Shinken.egg-info/PKG-INFO
Shinken.egg-info/SOURCES.txt
Shinken.egg-info/dependency_links.txt
Shinken.egg-info/not-zip-safe
Shinken.egg-info/requires.txt
Shinken.egg-info/top_level.txt
bin/launch_all.sh
bin/launch_all_debug.sh
bin/launch_arbiter.sh
bin/launch_arbiter_debug.sh
bin/launch_broker.sh
bin/launch_broker_debug.sh
bin/launch_poller.sh
bin/launch_poller_debug.sh
bin/launch_reactionner.sh
bin/launch_reactionner_debug.sh
bin/launch_receiver.sh
bin/launch_receiver_debug.sh
bin/launch_scheduler.sh
bin/launch_scheduler_debug.sh
bin/restart_all_debug.sh
bin/shinken
bin/shinken-arbiter
bin/shinken-arbiter.py
bin/shinken-broker
bin/shinken-broker.py
bin/shinken-discovery
bin/shinken-poller
bin/shinken-poller.py
bin/shinken-reactionner
bin/shinken-reactionner.py
bin/shinken-receiver
bin/shinken-receiver.py
bin/shinken-scheduler
bin/shinken-scheduler.py
bin/stop_all.sh
bin/stop_arbiter.sh
bin/stop_broker.sh
bin/stop_poller.sh
bin/stop_reactionner.sh
bin/stop_receiver.sh
bin/stop_scheduler.sh
bin/default/.gitignore
bin/default/shinken.in
bin/init.d/shinken
bin/init.d/shinken-arbiter
bin/init.d/shinken-broker
bin/init.d/shinken-poller
bin/init.d/shinken-reactionner
bin/init.d/shinken-receiver
bin/init.d/shinken-scheduler
bin/rc.d/shinken-arbiter
bin/rc.d/shinken-broker
bin/rc.d/shinken-poller
bin/rc.d/shinken-reactionner
bin/rc.d/shinken-receiver
bin/rc.d/shinken-scheduler
cli/desc/cli.py
cli/doc/cli.py
cli/shinkenio/cli.py
doc/howto.txt
doc/make.bat
doc/build/doctrees/environment.pickle
doc/build/doctrees/index.doctree
doc/build/doctrees/01_introduction/about.doctree
doc/build/doctrees/01_introduction/index.doctree
doc/build/doctrees/02_gettingstarted/beginners.doctree
doc/build/doctrees/02_gettingstarted/index.doctree
doc/build/doctrees/02_gettingstarted/upgrading-shinken.doctree
doc/build/doctrees/02_gettingstarted/installations/index.doctree
doc/build/doctrees/02_gettingstarted/installations/shinken-env-setup.doctree
doc/build/doctrees/02_gettingstarted/installations/shinken-first-steps.doctree
