Metadata-Version: 1.1
Name: Shinken
Version: 2.4.3
Summary: Shinken is a monitoring framework compatible with Nagios configuration and plugins
Home-page: http://www.shinken-monitoring.org
Author: Gabes Jean
Author-email: naparuba@gmail.com
License: GNU Affero General Public License
Platform: UNKNOWN
Classifier: Development Status :: 5 - Production/Stable
Classifier: Environment :: Console
Classifier: Intended Audience :: System Administrators
Classifier: License :: OSI Approved :: GNU Affero General Public License v3
Classifier: Operating System :: MacOS :: MacOS X
Classifier: Operating System :: Microsoft :: Windows
Classifier: Operating System :: POSIX
Classifier: Programming Language :: Python
Classifier: Topic :: System :: Monitoring
Classifier: Topic :: System :: Networking :: Monitoring
